maisie_sphinx_theme/__init__.py
maisie_sphinx_theme/maisie_sphinx_theme/comments.html
maisie_sphinx_theme/maisie_sphinx_theme/globaltoc.html
maisie_sphinx_theme/maisie_sphinx_theme/layout.html
maisie_sphinx_theme/maisie_sphinx_theme/localtoc.html
maisie_sphinx_theme/maisie_sphinx_theme/logo-text.html
maisie_sphinx_theme/maisie_sphinx_theme/search.html
maisie_sphinx_theme/maisie_sphinx_theme/searchbox.html
maisie_sphinx_theme/maisie_sphinx_theme/theme.conf
maisie_sphinx_theme/maisie_sphinx_theme/static/jquery.js
maisie_sphinx_theme/maisie_sphinx_theme/static/jquery.min.map
maisie_sphinx_theme/maisie_sphinx_theme/static/maisie.css_t
maisie_sphinx_theme/maisie_sphinx_theme/static/css/bootstrap-theme.min.css
maisie_sphinx_theme/maisie_sphinx_theme/static/css/bootstrap.min.css
maisie_sphinx_theme/maisie_sphinx_theme/static/fonts/glyphicons-halflings-regular.eot
maisie_sphinx_theme/maisie_sphinx_theme/static/fonts/glyphicons-halflings-regular.svg
maisie_sphinx_theme/maisie_sphinx_theme/static/fonts/glyphicons-halflings-regular.ttf
maisie_sphinx_theme/maisie_sphinx_theme/static/fonts/glyphicons-halflings-regular.woff
maisie_sphinx_theme/maisie_sphinx_theme/static/fonts/open-sans/stylesheet.css
maisie_sphinx_theme/maisie_sphinx_theme/static/fonts/open-sans/fonts/OpenSans-Bold-webfont.eot
maisie_sphinx_theme/maisie_sphinx_theme/static/fonts/open-sans/fonts/OpenSans-Bold-webfont.svg
maisie_sphinx_theme/maisie_sphinx_theme/static/fonts/open-sans/fonts/OpenSans-Bold-webfont.ttf
maisie_sphinx_theme/maisie_sphinx_theme/static/fonts/open-sans/fonts/OpenSans-Bold-webfont.woff
maisie_sphinx_theme/maisie_sphinx_theme/static/fonts/open-sans/fonts/OpenSans-BoldItalic-webfont.eot
maisie_sphinx_theme/maisie_sphinx_theme/static/fonts/open-sans/fonts/OpenSans-BoldItalic-webfont.svg
maisie_sphinx_theme/maisie_sphinx_theme/static/fonts/open-sans/fonts/OpenSans-BoldItalic-webfont.ttf
maisie_sphinx_theme/maisie_sphinx_theme/static/fonts/open-sans/fonts/OpenSans-BoldItalic-webfont.woff
Maisie_Sphinx_Theme-0.1.2.dist-info/LICENSE
Maisie_Sphinx_Theme-0.1.2.dist-info/METADATA
Maisie_Sphinx_Theme-0.1.2.dist-info/WHEEL
Maisie_Sphinx_Theme-0.1.2.dist-info/top_level.txt
Maisie_Sphinx_Theme-0.1.2.dist-info/RECORD
