Metadata-Version: 2.1
Name: Maisie-Sphinx-Theme
Version: 0.1.2
Summary: Sphinx theme used by Maisie.
Home-page: https://github.com/mkochanowski/maisie-sphinx-theme
Author: Marek Kochanowski
Author-email: maisie-sphinx-theme@kochanow.ski
License: MIT
Platform: UNKNOWN
Classifier: Intended Audience :: Developers
Classifier: License :: OSI Approved :: MIT License
Classifier: Programming Language :: Python
Requires-Dist: Sphinx (>1.3)
